aitor/__init__.py
aitor/aitor.py
aitor/aitorflows.py
aitor/llm.py
aitor/logging_config.py
aitor/memory.py
aitor/planning_agent.py
aitor/planning_reasoning.py
aitor/react_agent.py
aitor/reasoning.py
aitor/task.py
aitor/todo.py
aitor/tools.py
aitor-1.1.2.dist-info/licenses/LICENSE
aitor-1.1.2.dist-info/METADATA
aitor-1.1.2.dist-info/WHEEL
aitor-1.1.2.dist-info/top_level.txt
aitor-1.1.2.dist-info/RECORD
