Metadata-Version: 2.4
Name: aitor
Version: 1.1.2
Summary: A Python framework for building intelligent, memory-enabled agents with ReAct reasoning
Author-email: Ashfakh <ashfakhrithu@gmail.com>
License: MIT
Project-URL: Homepage, https://github.com/Ashfakh/aitor
Project-URL: Bug Tracker, https://github.com/Ashfakh/aitor/issues
Keywords: ai,workflow,builder,react,agents,llm
Classifier: Development Status :: 3 - Alpha
Classifier: Intended Audience :: Developers
Classifier: License :: OSI Approved :: MIT License
Classifier: Programming Language :: Python :: 3
Classifier: Programming Language :: Python :: 3.9
Classifier: Programming Language :: Python :: 3.10
Classifier: Programming Language :: Python :: 3.11
Classifier: Programming Language :: Python :: 3.12
Classifier: Programming Language :: Python :: 3.13
Requires-Python: >=3.9
License-File: LICENSE
Requires-Dist: openai>=1.0.0
Requires-Dist: anthropic>=0.25.0
Requires-Dist: psutil>=5.9.0
Requires-Dist: instructor>=1.0.0
Requires-Dist: pydantic>=2.0.0
Dynamic: license-file
